url_checker.py
fine_grained_url_checker/__init__.py
fine_grained_url_checker/core.py
Robo_Checker-0.1.0.dist-info/METADATA
Robo_Checker-0.1.0.dist-info/WHEEL
Robo_Checker-0.1.0.dist-info/top_level.txt
Robo_Checker-0.1.0.dist-info/RECORD
